blacksock/AreaManager.py
blacksock/ImageProcessing.py
blacksock/MidiManager.py
blacksock/VideoSource.py
blacksock/__main__.py
blacksock-0.1.0.dist-info/LICENSE
blacksock-0.1.0.dist-info/METADATA
blacksock-0.1.0.dist-info/WHEEL
blacksock-0.1.0.dist-info/top_level.txt
blacksock-0.1.0.dist-info/RECORD
